[
  {
    "id": "0aa0ad9a-a7ff-4aa0-8a0e-a049c3cf56b8",
    "name": "Kho sỉ Thập Nhất Phong",
    "phone": null,
    "address": "An Thạnh, Đồng Tháp",
    "email": null,
    "taxCode": null,
    "contactPerson": null,
    "notes": null,
    "isActive": true,
    "created_by": null,
    "updated_by": null,
    "created_at": "2025-11-28T06:36:42.995+00:00",
    "updated_at": "2025-11-28T06:36:43.347705+00:00"
  },
  {
    "id": "5484c158-7605-4978-99c9-c66509c34337",
    "name": "Đại lý Suzuki",
    "phone": null,
    "address": "P. Hồng Ngự, Đồng Tháp",
    "email": null,
    "taxCode": null,
    "contactPerson": null,
    "notes": null,
    "isActive": true,
    "created_by": null,
    "updated_by": null,
    "created_at": "2025-11-29T05:38:42.225+00:00",
    "updated_at": "2025-11-29T05:38:42.890668+00:00"
  },
  {
    "id": "64c0754d-dfe4-4596-a06b-318d6a684ff5",
    "name": "Yamaha Thập Nhất Phong",
    "phone": null,
    "address": "P. Hồng Ngự, Đồng Tháp",
    "email": null,
    "taxCode": null,
    "contactPerson": null,
    "notes": null,
    "isActive": true,
    "created_by": null,
    "updated_by": null,
    "created_at": "2025-11-29T05:39:38.534+00:00",
    "updated_at": "2025-11-29T05:39:39.003487+00:00"
  },
  {
    "id": "4d67bbb9-2e74-4395-914f-f1abbd5e02ef",
    "name": "Cty TNHH Phước Lộc Phát 99",
    "phone": "0939821556",
    "address": "Lấp Vò - Đồng Tháp",
    "email": null,
    "taxCode": null,
    "contactPerson": null,
    "notes": null,
    "isActive": true,
    "created_by": null,
    "updated_by": null,
    "created_at": "2025-11-29T06:12:17.809+00:00",
    "updated_at": "2025-11-29T06:12:18.096296+00:00"
  },
  {
    "id": "0d951f33-2b3e-40e9-bb27-391949140282",
    "name": "Vỏ ruột Thanh Hải",
    "phone": "0707456793",
    "address": "HCM",
    "email": null,
    "taxCode": null,
    "contactPerson": null,
    "notes": null,
    "isActive": true,
    "created_by": null,
    "updated_by": null,
    "created_at": "2025-11-29T06:34:57.684+00:00",
    "updated_at": "2025-11-29T06:34:58.329544+00:00"
  },
  {
    "id": "3c6b172b-144f-495a-a013-8afce2094ea0",
    "name": "Cty TNHH TM-DV Phương Thuỷ",
    "phone": "0907855077",
    "address": "Q7, TPHCM",
    "email": null,
    "taxCode": null,
    "contactPerson": null,
    "notes": null,
    "isActive": true,
    "created_by": null,
    "updated_by": null,
    "created_at": "2025-11-29T07:01:50.448+00:00",
    "updated_at": "2025-11-29T07:01:50.728261+00:00"
  },
  {
    "id": "4918617e-eaba-4e0f-a162-3048253a9a91",
    "name": "Minh Phong Auto",
    "phone": "1900232434",
    "address": "HCM",
    "email": null,
    "taxCode": null,
    "contactPerson": null,
    "notes": null,
    "isActive": true,
    "created_by": null,
    "updated_by": null,
    "created_at": "2025-11-29T07:05:34.773+00:00",
    "updated_at": "2025-11-29T07:05:34.973475+00:00"
  },
  {
    "id": "e54c8179-438b-4cd4-a5e6-a04ae88c2a57",
    "name": "Nhạn-Lâm SmartCare",
    "phone": "",
    "address": "",
    "email": null,
    "taxCode": null,
    "contactPerson": null,
    "notes": null,
    "isActive": true,
    "created_by": null,
    "updated_by": null,
    "created_at": "2025-12-01T03:30:01.615+00:00",
    "updated_at": "2025-12-01T03:30:02.602524+00:00"
  },
  {
    "id": "8b5ff67e-1758-4a48-89b7-607d3e4ea30f",
    "name": "Hưng Phát",
    "phone": "0988971627",
    "address": null,
    "email": null,
    "taxCode": null,
    "contactPerson": null,
    "notes": null,
    "isActive": true,
    "created_by": null,
    "updated_by": null,
    "created_at": "2025-12-01T09:07:22.304+00:00",
    "updated_at": "2025-12-01T09:07:22.665127+00:00"
  },
  {
    "id": "1bae3ad1-726a-47cc-8824-d50ab9606975",
    "name": "Chú Thông Phụ Tùng",
    "phone": null,
    "address": "P. Hồng Ngự, Đồng Tháp.",
    "email": null,
    "taxCode": null,
    "contactPerson": null,
    "notes": null,
    "isActive": true,
    "created_by": null,
    "updated_by": null,
    "created_at": "2025-12-01T09:25:46.638+00:00",
    "updated_at": "2025-12-01T09:25:46.997719+00:00"
  },
  {
    "id": "4d1b350e-2aa1-4437-a962-85c7e4feb0fe",
    "name": "Kim Thành (Dung)",
    "phone": "0941057729",
    "address": "Hồng Ngự",
    "email": null,
    "taxCode": null,
    "contactPerson": null,
    "notes": null,
    "isActive": true,
    "created_by": null,
    "updated_by": null,
    "created_at": "2025-12-02T06:23:21.6+00:00",
    "updated_at": "2025-12-02T06:23:22.324929+00:00"
  },
  {
    "id": "b1daa30e-a0a9-43df-9a96-fc9de4247fce",
    "name": "Shopee",
    "phone": null,
    "address": null,
    "email": null,
    "taxCode": null,
    "contactPerson": null,
    "notes": null,
    "isActive": true,
    "created_by": null,
    "updated_by": null,
    "created_at": "2025-12-11T03:12:31.746+00:00",
    "updated_at": "2025-12-11T03:12:31.963823+00:00"
  },
  {
    "id": "a27f7891-c57b-42ed-a328-56342bf31ce1",
    "name": "Minh Quân xe điện Sài Gòn",
    "phone": null,
    "address": null,
    "email": null,
    "taxCode": null,
    "contactPerson": null,
    "notes": null,
    "isActive": true,
    "created_by": null,
    "updated_by": null,
    "created_at": "2025-12-25T05:31:27.6+00:00",
    "updated_at": "2025-12-25T05:31:29.270373+00:00"
  },
  {
    "id": "c0f1f2e9-3348-40f1-afb6-d2b092c3dbf5",
    "name": "Tổng kho phụ tùng Hà Nội",
    "phone": "0963478675",
    "address": "Hà Nội",
    "email": null,
    "taxCode": null,
    "contactPerson": null,
    "notes": null,
    "isActive": true,
    "created_by": null,
    "updated_by": null,
    "created_at": "2025-12-27T05:39:24.819+00:00",
    "updated_at": "2025-12-27T05:39:26.286807+00:00"
  },
  {
    "id": "f9fb4f1b-ad49-4eff-9216-3037e0ef44fd",
    "name": "Phụ Tùng Hiền Hà Nội",
    "phone": null,
    "address": null,
    "email": null,
    "taxCode": null,
    "contactPerson": null,
    "notes": null,
    "isActive": true,
    "created_by": null,
    "updated_by": null,
    "created_at": "2025-12-27T06:44:49.972+00:00",
    "updated_at": "2025-12-27T06:44:51.262563+00:00"
  },
  {
    "id": "5617c4ad-1bb5-4ea1-a774-3c31bf753b0c",
    "name": "Cty CP TM Song Đại Long",
    "phone": "02877777369",
    "address": "Khu phố 1, P. An Khánh, TP. Thủ Đức, Tp.HCM",
    "email": null,
    "taxCode": null,
    "contactPerson": null,
    "notes": null,
    "isActive": true,
    "created_by": null,
    "updated_by": null,
    "created_at": "2025-12-27T10:08:11.132+00:00",
    "updated_at": "2025-12-27T10:08:11.883605+00:00"
  },
  {
    "id": "d41ccd06-ecf5-4f71-b54c-d0d3c0210ace",
    "name": "Phụ tùng xe điện Xinshuosh",
    "phone": "0816998811",
    "address": "khu 4 thị trấn Thanh Thủy, Thanh Thủy, Phú Thọ",
    "email": null,
    "taxCode": null,
    "contactPerson": null,
    "notes": null,
    "isActive": true,
    "created_by": null,
    "updated_by": null,
    "created_at": "2026-01-10T08:38:15.449+00:00",
    "updated_at": "2026-01-10T08:38:16.575465+00:00"
  },
  {
    "id": "50171644-0ff4-453a-a830-c5f56d4178eb",
    "name": "Head Trung Tâm 1",
    "phone": null,
    "address": null,
    "email": null,
    "taxCode": null,
    "contactPerson": null,
    "notes": null,
    "isActive": true,
    "created_by": null,
    "updated_by": null,
    "created_at": "2026-01-12T01:51:24.842+00:00",
    "updated_at": "2026-01-12T01:51:24.534282+00:00"
  },
  {
    "id": "af9f7d4d-07e8-491e-9859-c1c849ff73f8",
    "name": "Hà Hoài Phụ tùng Hà Nội",
    "phone": null,
    "address": null,
    "email": null,
    "taxCode": null,
    "contactPerson": null,
    "notes": null,
    "isActive": true,
    "created_by": null,
    "updated_by": null,
    "created_at": "2026-01-31T03:57:45.556+00:00",
    "updated_at": "2026-01-31T03:57:46.738226+00:00"
  },
  {
    "id": "7d04fa53-53d0-4d6f-8390-014ac913f22c",
    "name": "Thanh Hải vỏ xe casumina",
    "phone": null,
    "address": null,
    "email": null,
    "taxCode": null,
    "contactPerson": null,
    "notes": null,
    "isActive": true,
    "created_by": null,
    "updated_by": null,
    "created_at": "2026-02-08T07:02:39.048+00:00",
    "updated_at": "2026-02-08T07:02:41.600252+00:00"
  },
  {
    "id": "9cee5ad3-c6a0-4570-9feb-b2009e782e84",
    "name": "Xinh phụ tùng Hà Nội",
    "phone": null,
    "address": null,
    "email": null,
    "taxCode": null,
    "contactPerson": null,
    "notes": null,
    "isActive": true,
    "created_by": null,
    "updated_by": null,
    "created_at": "2026-02-27T06:58:29.257+00:00",
    "updated_at": "2026-02-27T06:58:29.672281+00:00"
  },
  {
    "id": "ecbdda4b-62ac-4994-8e3d-54f8c8e12888",
    "name": "CONG TY TNHH PHU TUNG LIEN LUC DIA",
    "phone": null,
    "address": null,
    "email": null,
    "taxCode": null,
    "contactPerson": null,
    "notes": null,
    "isActive": true,
    "created_by": null,
    "updated_by": null,
    "created_at": "2026-03-03T03:08:15.924+00:00",
    "updated_at": "2026-03-03T03:08:17.605156+00:00"
  },
  {
    "id": "d6490eff-1483-43a5-87f8-ff6a607a6521",
    "name": "Quỳnh Như (NSD RK)",
    "phone": "0969648656",
    "address": null,
    "email": null,
    "taxCode": null,
    "contactPerson": null,
    "notes": null,
    "isActive": true,
    "created_by": null,
    "updated_by": null,
    "created_at": "2026-04-27T01:29:29.961+00:00",
    "updated_at": "2026-04-27T01:29:32.448055+00:00"
  },
  {
    "id": "6c0396d1-098f-4352-8d8b-ad879a7482f6",
    "name": "Phụ tùng xe điện Dân Việt",
    "phone": "0968922248",
    "address": null,
    "email": null,
    "taxCode": null,
    "contactPerson": null,
    "notes": null,
    "isActive": true,
    "created_by": null,
    "updated_by": null,
    "created_at": "2026-05-09T06:59:52.094+00:00",
    "updated_at": "2026-05-09T06:59:52.128553+00:00"
  },
  {
    "id": "55a90bfc-e22c-4fe9-9df9-8be7c93be574",
    "name": "Phụ tùng xe điện Anh Tiến",
    "phone": "0359663199",
    "address": null,
    "email": null,
    "taxCode": null,
    "contactPerson": null,
    "notes": null,
    "isActive": true,
    "created_by": null,
    "updated_by": null,
    "created_at": "2026-06-20T03:33:56.165+00:00",
    "updated_at": "2026-06-20T03:33:56.658381+00:00"
  },
  {
    "id": "03c5c63e-3bd1-4e18-9bb1-d72602393e95",
    "name": "Phụ tùng xe máy Thúy Dũng",
    "phone": "0329992018",
    "address": null,
    "email": null,
    "taxCode": null,
    "contactPerson": null,
    "notes": null,
    "isActive": true,
    "created_by": null,
    "updated_by": null,
    "created_at": "2026-06-23T03:19:12.621+00:00",
    "updated_at": "2026-06-23T03:19:13.19243+00:00"
  },
  {
    "id": "922110dc-ac17-4763-99e7-a9fd764454cb",
    "name": "Cty Thành Tài Motor",
    "phone": "0868660777",
    "address": null,
    "email": null,
    "taxCode": null,
    "contactPerson": null,
    "notes": null,
    "isActive": true,
    "created_by": null,
    "updated_by": null,
    "created_at": "2026-06-26T09:40:11.667+00:00",
    "updated_at": "2026-06-26T09:40:11.341776+00:00"
  }
]